{
    "funding": [
        {
            "fundingId": 1,
            "targetId": 1,
            "targetName": "철수",
            "product": {
                "productId": 4,
                "name": "삼성전자 그랑데 AI 의류 건조기",
                "productImageUrl": "https://img.29cm.co.kr/next-product/2022/08/18/979c9bfa22db4720996608688d8b9ff0_20220818171330.jpg?width=700",
                "price": 1106110
            },
            "fundedPrice": 840000,
            "myfundingPrice": 20000,
            "participants": ["짱구", "맹구", "훈이", "유리"],
            "fundStatus": "Ing",
            "startDate": "2023-02-18T11:46:49.102644",
            "endDate": "2023-02-18T11:46:49.102644"
        },
        {
            "fundingId": 2,
            "targetId": 1,
            "targetName": "철수",
            "product": {
                "productId": 4,
                "name": "삼성전자 그랑데 AI 의류 건조기",
                "productImageUrl": "https://img.29cm.co.kr/next-product/2022/08/18/979c9bfa22db4720996608688d8b9ff0_20220818171330.jpg?width=700",
                "price": 1106110
            },
            "fundedPrice": 840000,
            "myfundingPrice": 20000,
            "participants": ["짱구", "맹구", "훈이", "유리"],
            "fundStatus": "Ing",
            "startDate": "2023-02-18T11:46:49.102644",
            "endDate": "2023-02-18T11:46:49.102644"
        },
        {
            "fundingId": 3,
            "targetId": 1,
            "targetName": "철수",
            "product": {
                "productId": 4,
                "name": "삼성전자 그랑데 AI 의류 건조기",
                "productImageUrl": "https://img.29cm.co.kr/next-product/2022/08/18/979c9bfa22db4720996608688d8b9ff0_20220818171330.jpg?width=700",
                "price": 1106110
            },
            "fundedPrice": 840000,
            "myfundingPrice": 20000,
            "participants": ["짱구", "맹구", "훈이", "유리"],
            "fundStatus": "Ing",
            "startDate": "2023-02-18T11:46:49.102644",
            "endDate": "2023-02-18T11:46:49.102644"
        },
        {
            "fundingId": 4,
            "targetId": 1,
            "targetName": "철수",
            "product": {
                "productId": 4,
                "name": "삼성전자 그랑데 AI 의류 건조기",
                "productImageUrl": "https://img.29cm.co.kr/next-product/2022/08/18/979c9bfa22db4720996608688d8b9ff0_20220818171330.jpg?width=700",
                "price": 1106110
            },
            "fundedPrice": 840000,
            "myfundingPrice": 20000,
            "participants": ["짱구", "맹구", "훈이", "유리"],
            "fundStatus": "Ing",
            "startDate": "2023-02-18T11:46:49.102644",
            "endDate": "2023-02-18T11:46:49.102644"
        },
        {
            "fundingId": 5,
            "targetId": 1,
            "targetName": "철수",
            "product": {
                "productId": 4,
                "name": "삼성전자 그랑데 AI 의류 건조기",
                "productImageUrl": "https://img.29cm.co.kr/next-product/2022/08/18/979c9bfa22db4720996608688d8b9ff0_20220818171330.jpg?width=700",
                "price": 1106110
            },
            "fundedPrice": 840000,
            "myfundingPrice": 20000,
            "participants": ["짱구", "맹구", "훈이", "유리"],
            "fundStatus": "Ing",
            "startDate": "2023-02-18T11:46:49.102644",
            "endDate": "2023-02-18T11:46:49.102644"
        },
        {
            "fundingId": 6,
            "targetId": 1,
            "targetName": "철수",
            "product": {
                "productId": 4,
                "name": "삼성전자 그랑데 AI 의류 건조기",
                "productImageUrl": "https://img.29cm.co.kr/next-product/2022/08/18/979c9bfa22db4720996608688d8b9ff0_20220818171330.jpg?width=700",
                "price": 1106110
            },
            "fundedPrice": 840000,
            "myfundingPrice": 20000,
            "participants": ["짱구", "맹구", "훈이", "유리"],
            "fundStatus": "Ing",
            "startDate": "2023-02-18T11:46:49.102644",
            "endDate": "2023-02-18T11:46:49.102644"
        },
        {
            "fundingId": 7,
            "targetId": 1,
            "targetName": "철수",
            "product": {
                "productId": 4,
                "name": "삼성전자 그랑데 AI 의류 건조기",
                "productImageUrl": "https://img.29cm.co.kr/next-product/2022/08/18/979c9bfa22db4720996608688d8b9ff0_20220818171330.jpg?width=700",
                "price": 1106110
            },
            "fundedPrice": 840000,
            "myfundingPrice": 20000,
            "participants": ["짱구", "맹구", "훈이", "유리"],
            "fundStatus": "Ing",
            "startDate": "2023-02-18T11:46:49.102644",
            "endDate": "2023-02-18T11:46:49.102644"
        },
        {
            "fundingId": 8,
            "targetId": 1,
            "targetName": "철수",
            "product": {
                "productId": 4,
                "name": "삼성전자 그랑데 AI 의류 건조기",
                "productImageUrl": "https://img.29cm.co.kr/next-product/2022/08/18/979c9bfa22db4720996608688d8b9ff0_20220818171330.jpg?width=700",
                "price": 1106110
            },
            "fundedPrice": 840000,
            "myfundingPrice": 20000,
            "participants": ["짱구", "맹구", "훈이", "유리"],
            "fundStatus": "Ing",
            "startDate": "2023-02-18T11:46:49.102644",
            "endDate": "2023-02-18T11:46:49.102644"
        },
        {
            "fundingId": 9,
            "targetId": 1,
            "targetName": "철수",
            "product": {
                "productId": 4,
                "name": "삼성전자 그랑데 AI 의류 건조기",
                "productImageUrl": "https://img.29cm.co.kr/next-product/2022/08/18/979c9bfa22db4720996608688d8b9ff0_20220818171330.jpg?width=700",
                "price": 1106110
            },
            "fundedPrice": 840000,
            "myfundingPrice": 20000,
            "participants": ["짱구", "맹구", "훈이", "유리"],
            "fundStatus": "Ing",
            "startDate": "2023-02-18T11:46:49.102644",
            "endDate": "2023-02-18T11:46:49.102644"
        },
        {
            "fundingId": 10,
            "targetId": 1,
            "targetName": "철수",
            "product": {
                "productId": 4,
                "name": "삼성전자 그랑데 AI 의류 건조기",
                "productImageUrl": "https://img.29cm.co.kr/next-product/2022/08/18/979c9bfa22db4720996608688d8b9ff0_20220818171330.jpg?width=700",
                "price": 1106110
            },
            "fundedPrice": 840000,
            "myfundingPrice": 20000,
            "participants": ["짱구", "맹구", "훈이", "유리"],
            "fundStatus": "Ing",
            "startDate": "2023-02-18T11:46:49.102644",
            "endDate": "2023-02-18T11:46:49.102644"
        },
        {
            "fundingId": 11,
            "targetId": 1,
            "targetName": "철수",
            "product": {
                "productId": 4,
                "name": "삼성전자 그랑데 AI 의류 건조기",
                "productImageUrl": "https://img.29cm.co.kr/next-product/2022/08/18/979c9bfa22db4720996608688d8b9ff0_20220818171330.jpg?width=700",
                "price": 1106110
            },
            "fundedPrice": 840000,
            "myfundingPrice": 20000,
            "participants": ["짱구", "맹구", "훈이", "유리"],
            "fundStatus": "Ing",
            "startDate": "2023-02-18T11:46:49.102644",
            "endDate": "2023-02-18T11:46:49.102644"
        },
        {
            "fundingId": 12,
            "targetId": 1,
            "targetName": "철수",
            "product": {
                "productId": 4,
                "name": "삼성전자 그랑데 AI 의류 건조기",
                "productImageUrl": "https://img.29cm.co.kr/next-product/2022/08/18/979c9bfa22db4720996608688d8b9ff0_20220818171330.jpg?width=700",
                "price": 1106110
            },
            "fundedPrice": 840000,
            "myfundingPrice": 20000,
            "participants": ["짱구", "맹구", "훈이", "유리"],
            "fundStatus": "Ing",
            "startDate": "2023-02-18T11:46:49.102644",
            "endDate": "2023-02-18T11:46:49.102644"
        },
        {
            "fundingId": 13,
            "targetId": 1,
            "targetName": "철수",
            "product": {
                "productId": 4,
                "name": "삼성전자 그랑데 AI 의류 건조기",
                "productImageUrl": "https://img.29cm.co.kr/next-product/2022/08/18/979c9bfa22db4720996608688d8b9ff0_20220818171330.jpg?width=700",
                "price": 1106110
            },
            "fundedPrice": 840000,
            "myfundingPrice": 20000,
            "participants": ["짱구", "맹구", "훈이", "유리"],
            "fundStatus": "Ing",
            "startDate": "2023-02-18T11:46:49.102644",
            "endDate": "2023-02-18T11:46:49.102644"
        },
        {
            "fundingId": 14,
            "targetId": 1,
            "targetName": "철수",
            "product": {
                "productId": 4,
                "name": "삼성전자 그랑데 AI 의류 건조기",
                "productImageUrl": "https://img.29cm.co.kr/next-product/2022/08/18/979c9bfa22db4720996608688d8b9ff0_20220818171330.jpg?width=700",
                "price": 1106110
            },
            "fundedPrice": 840000,
            "myfundingPrice": 20000,
            "participants": ["짱구", "맹구", "훈이", "유리"],
            "fundStatus": "Ing",
            "startDate": "2023-02-18T11:46:49.102644",
            "endDate": "2023-02-18T11:46:49.102644"
        },
        {
            "fundingId": 15,
            "targetId": 1,
            "targetName": "철수",
            "product": {
                "productId": 4,
                "name": "삼성전자 그랑데 AI 의류 건조기",
                "productImageUrl": "https://img.29cm.co.kr/next-product/2022/08/18/979c9bfa22db4720996608688d8b9ff0_20220818171330.jpg?width=700",
                "price": 1106110
            },
            "fundedPrice": 840000,
            "myfundingPrice": 20000,
            "participants": ["짱구", "맹구", "훈이", "유리"],
            "fundStatus": "Ing",
            "startDate": "2023-02-18T11:46:49.102644",
            "endDate": "2023-02-18T11:46:49.102644"
        },
        {
            "fundingId": 16,
            "targetId": 1,
            "targetName": "철수",
            "product": {
                "productId": 4,
                "name": "삼성전자 그랑데 AI 의류 건조기",
                "productImageUrl": "https://img.29cm.co.kr/next-product/2022/08/18/979c9bfa22db4720996608688d8b9ff0_20220818171330.jpg?width=700",
                "price": 1106110
            },
            "fundedPrice": 840000,
            "myfundingPrice": 20000,
            "participants": ["짱구", "맹구", "훈이", "유리"],
            "fundStatus": "Ing",
            "startDate": "2023-02-18T11:46:49.102644",
            "endDate": "2023-02-18T11:46:49.102644"
        },
        {
            "fundingId": 17,
            "targetId": 1,
            "targetName": "철수",
            "product": {
                "productId": 4,
                "name": "삼성전자 그랑데 AI 의류 건조기",
                "productImageUrl": "https://img.29cm.co.kr/next-product/2022/08/18/979c9bfa22db4720996608688d8b9ff0_20220818171330.jpg?width=700",
                "price": 1106110
            },
            "fundedPrice": 840000,
            "myfundingPrice": 20000,
            "participants": ["짱구", "맹구", "훈이", "유리"],
            "fundStatus": "Ing",
            "startDate": "2023-02-18T11:46:49.102644",
            "endDate": "2023-02-18T11:46:49.102644"
        }
    ]
}
